gpxfix/__init__.py
gpxfix/main.py
gpxfix-0.0.5.data/scripts/gpxfix
gpxfix-0.0.5.dist-info/LICENSE
gpxfix-0.0.5.dist-info/METADATA
gpxfix-0.0.5.dist-info/WHEEL
gpxfix-0.0.5.dist-info/top_level.txt
gpxfix-0.0.5.dist-info/RECORD
