Metadata-Version: 2.1
Name: gpxfix
Version: 0.0.5
Summary: gpxfix: GUI to fix .gpx tracks with missing sections
Home-page: https://github.com/jannisborn/gpxfix
Author: Jannis Born
Author-email: jannis.born@gmx.de
License: MIT
Keywords: GPX,Tracking,Sports,Running,Cycling,Strava
Classifier: Intended Audience :: Developers
Classifier: License :: OSI Approved :: MIT License
Classifier: Programming Language :: Python :: 3
Classifier: Programming Language :: Python :: 3.7
Classifier: Topic :: Software Development :: Libraries :: Python Modules
License-File: LICENSE
Requires-Dist: numpy
Requires-Dist: gpxpy (>=1.3.5)
Requires-Dist: matplotlib
